AUTHORS
CHANGES
LICENSE
README
TODO
ez_setup.py
setup.cfg
setup.py
examples/get_page.py
examples/get_title.py
lib/WebChuan.egg-info/PKG-INFO
lib/WebChuan.egg-info/SOURCES.txt
lib/WebChuan.egg-info/dependency_links.txt
lib/WebChuan.egg-info/not-zip-safe
lib/WebChuan.egg-info/requires.txt
lib/WebChuan.egg-info/top_level.txt
lib/webchuan/__init__.py
lib/webchuan/base.py
lib/webchuan/bin.py
lib/webchuan/decorator.py
lib/webchuan/element.py
lib/webchuan/interface.py
lib/webchuan/observer.py