Metadata-Version: 1.0
Name: WebChuan
Version: 0.0.1.dev-r22
Summary: Library and tools for getting and parsing web
Home-page: http://webchuan.ez2learn.com
Author: Victor Lin
Author-email: bornstub@gmail.com
License: MIT License
Platform: UNKNOWN
Classifier: Development Status :: 1 - Planning
Classifier: Intended Audience :: Developers
Classifier: License :: OSI Approved :: MIT License
Classifier: Operating System :: OS Independent
Classifier: Programming Language :: Python
Classifier: Topic :: Internet :: WWW/HTTP
Classifier: Topic :: Software Development :: Libraries :: Python Modules
